[
	{
		"name": "uploadPhoto",
		"url": "/photo",
		"method": "post",
		"params": ["photo"],
		"headers": {
			"Content-Type": "multipart/form-data"
		},
		"timeout": 0
	},
	{
		"name": "getPhotos",
		"url": "/photos",
		"method": "get",
		"params": ["limit", "offset"]
	},
	{
		"name": "getPhoto",
		"url": "/photo/{drive_name}",
		"method": "get"
	},
	{
		"name": "deletePhotos",
		"url": "/photos",
		"method": "delete",
		"params": ["ids"]
	},
	{
		"name": "getSinglePhoto",
		"url": "/key/{key}",
		"method": "get"
	},
	{
		"name": "download",
		"url": "/download",
		"method": "post",
		"params": ["url"],
		"timeout": 30000
	},
	{
		"name": "getPrivateWhiteHole",
		"url": "/white-hole/private/{key}",
		"method": "get"
	},
	{
		"name": "getPublicWhiteHole",
		"url": "/white-hole/public/{key}",
		"method": "get"
	},
	{
		"name": "getWhiteHoles",
		"url": "/white-holes",
		"method": "get",
		"params": ["limit", "offset"]
	},
	{
		"name": "createWhiteHole",
		"url": "/white-hole",
		"method": "post",
		"params": ["images", "is_public", "name"]
	},
	{
		"name": "editWhiteHole",
		"url": "/white-hole/{key}",
		"method": "put",
		"params": ["is_public"]
	},
	{
		"name": "deleteWhiteHole",
		"url": "/white-hole/{key}",
		"method": "delete"
	},
	{
		"name": "deletePhotosFromWhiteHole",
		"url": "/white-hole/photos",
		"method": "delete",
		"params": ["white_hole_key", "ids"]
	},
	{
		"name": "addPhotosToWhiteHole",
		"url": "/white-hole/photos",
		"method": "put",
		"params": ["white_hole_key", "ids"]
	},
	{
		"name": "createIntegration",
		"url": "/integration",
		"method": "post",
		"params": ["name"]
	},
	{
		"name": "deleteIntegration",
		"url": "/integration",
		"method": "delete",
		"params": ["key"]
	},
	{
		"name": "getIntegrations",
		"url": "/integration",
		"method": "get"
	},
	{
		"name": "searchSurfer",
		"url": "/search-surfer",
		"method": "get",
		"params": ["query", "results"]
	},
	{
		"name": "getSettings",
		"url": "/settings",
		"method": "get"
	},
	{
		"name": "setSettings",
		"url": "/settings",
		"method": "put",
		"params": ["key", "value"]
	}
]
